winstools/__init__.py
winstools/aaa.py
winstools-0.0.12.dist-info/METADATA
winstools-0.0.12.dist-info/WHEEL
winstools-0.0.12.dist-info/top_level.txt
winstools-0.0.12.dist-info/RECORD
