Metadata-Version: 2.1
Name: winstools
Version: 0.0.12
Summary: HoHo
Home-page: 
Author: Winstang
Author-email: 
